{
  "sections": {
    "15d9c212-6ce8-4fd0-9cf9-c773090bb162": {
      "type": "slideshow",
      "blocks": {
        "slideshow_rFDgc6": {
          "type": "slideshow",
          "disabled": true,
          "settings": {
            "link": "shopify:\/\/pages\/aniversario",
            "image_desktop": "shopify:\/\/shop_images\/banner-aniversario-desktop_1.png",
            "image_tablet": "shopify:\/\/shop_images\/banner-aniversario-mobile.png",
            "image_mobile": "shopify:\/\/shop_images\/banner-aniversario-mobile.png",
            "alt_text": ""
          }
        },
        "slideshow_TGYnaW": {
          "type": "slideshow",
          "settings": {
            "link": "shopify:\/\/products\/almohadilla-lumbar-inteligente-scaldasonno",
            "image_desktop": "shopify:\/\/shop_images\/lumbar_banner_1.png",
            "image_tablet": "shopify:\/\/shop_images\/lumbar_mobile.png",
            "image_mobile": "shopify:\/\/shop_images\/lumbar_mobile.png",
            "alt_text": ""
          }
        },
        "slideshow_mGchAd": {
          "type": "slideshow",
          "settings": {
            "link": "shopify:\/\/collections\/mantas-electricas",
            "image_desktop": "shopify:\/\/shop_images\/manta_gris_banner_1.png",
            "image_tablet": "shopify:\/\/shop_images\/manta_gris_mobile.png",
            "image_mobile": "shopify:\/\/shop_images\/manta_gris_mobile.png",
            "alt_text": ""
          }
        },
        "slideshow_4HdVd6": {
          "type": "slideshow",
          "settings": {
            "link": "shopify:\/\/collections\/calor-textil",
            "image_desktop": "shopify:\/\/shop_images\/ecoadapto_banner_1.png",
            "image_tablet": "shopify:\/\/shop_images\/ecoadapto_mobile.png",
            "image_mobile": "shopify:\/\/shop_images\/ecoadapto_mobile.png",
            "alt_text": ""
          }
        },
        "slideshow_mYq6CR": {
          "type": "slideshow",
          "settings": {
            "link": "shopify:\/\/collections\/almohadillas",
            "image_desktop": "shopify:\/\/shop_images\/cervical_desktop.png",
            "image_tablet": "shopify:\/\/shop_images\/cervical_mobile.png",
            "image_mobile": "shopify:\/\/shop_images\/cervical_mobile.png",
            "alt_text": ""
          }
        },
        "slideshow_BikDJr": {
          "type": "slideshow",
          "disabled": true,
          "settings": {
            "link": "shopify:\/\/collections\/calientacamas",
            "image_desktop": "shopify:\/\/shop_images\/ACTIVE_DESKTOP.jpg",
            "image_tablet": "shopify:\/\/shop_images\/ACTIVE_MOBILE_af67fd88-20bb-42ed-904d-433d410c46ee.jpg",
            "image_mobile": "shopify:\/\/shop_images\/ACTIVE_MOBILE.jpg",
            "alt_text": "Calientacamas Active Scaldasonno"
          }
        },
        "slideshow_drHM96": {
          "type": "slideshow",
          "disabled": true,
          "settings": {
            "link": "shopify:\/\/collections\/almohadillas",
            "image_desktop": "shopify:\/\/shop_images\/ALMOHADILLAS_DESKTOP.jpg",
            "image_tablet": "shopify:\/\/shop_images\/ALMOHADILLAS_MOBILE_696111a1-071c-458b-a1e1-d0b69eb37a40.jpg",
            "image_mobile": "shopify:\/\/shop_images\/ALMOHADILLAS_MOBILE_696111a1-071c-458b-a1e1-d0b69eb37a40.jpg",
            "alt_text": "Almohadillas scaldasonno"
          }
        }
      },
      "block_order": [
        "slideshow_rFDgc6",
        "slideshow_TGYnaW",
        "slideshow_mGchAd",
        "slideshow_4HdVd6",
        "slideshow_mYq6CR",
        "slideshow_BikDJr",
        "slideshow_drHM96"
      ],
      "settings": {}
    },
    "4e0fee28-e16c-4802-9402-cc8e410a5f50": {
      "type": "home-iconos",
      "blocks": {
        "99bef9f3-d4e5-46df-8c4a-dac0140fddf8": {
          "type": "icon",
          "settings": {
            "image": "shopify:\/\/shop_images\/Sin_titulo-2_Mesa_de_trabajo_1_2.png",
            "text": "Servicio al cliente"
          }
        },
        "89b2f0c6-fd3b-403e-b9f6-65fec5b20390": {
          "type": "icon",
          "settings": {
            "image": "shopify:\/\/shop_images\/Sin_titulo-2-03_2.png",
            "text": "Despachos"
          }
        },
        "0d221d6a-7364-4b9c-ad00-6b4a9dba3c5a": {
          "type": "icon",
          "settings": {
            "image": "shopify:\/\/shop_images\/Sin_titulo-2-02_2.png",
            "text": "Medios de pago"
          }
        },
        "ff641f0b-3a38-4123-b6c0-cdced1e3f475": {
          "type": "icon",
          "settings": {
            "image": "shopify:\/\/shop_images\/Sin_titulo-2-04_1.png",
            "text": "Garantía de satisfacción"
          }
        }
      },
      "block_order": [
        "99bef9f3-d4e5-46df-8c4a-dac0140fddf8",
        "89b2f0c6-fd3b-403e-b9f6-65fec5b20390",
        "0d221d6a-7364-4b9c-ad00-6b4a9dba3c5a",
        "ff641f0b-3a38-4123-b6c0-cdced1e3f475"
      ],
      "settings": {}
    },
    "countdown_TiaGXg": {
      "type": "countdown",
      "disabled": true,
      "settings": {
        "target_date": "2024-10-02 17:59:59",
        "image_mobile": "shopify:\/\/shop_images\/banner-pocashoras-calientapies-mobile.png",
        "image_desktop": "shopify:\/\/shop_images\/banner-pocashoras-calientapies-desktop_1.png",
        "title": "¡solo por pocas horas!",
        "link": "shopify:\/\/products\/calientapies-gris-scaldasonno"
      }
    },
    "main": {
      "type": "main-index",
      "settings": {}
    },
    "6d039727-5eef-443e-a084-d2a448f903cb": {
      "type": "home-hero",
      "disabled": true,
      "settings": {
        "image_desktop": "shopify:\/\/shop_images\/home-desktop_2.jpg",
        "image_tablet": "shopify:\/\/shop_images\/home-tablet_1.jpg",
        "image_mobile": "shopify:\/\/shop_images\/home-movil_1.jpg",
        "title": "Scaldasonno",
        "bajada": "El calor que siempre haz soñado",
        "gradient_ini": "#ffffff",
        "gradient_end": "#ffffff",
        "title_color": "#4a4a49",
        "text_color": "#4a4a49",
        "button_color": "#4a4a49",
        "button_text_color": "#ffffff",
        "button_text": "Descubre más",
        "button_link": "shopify:\/\/collections\/calientacamas"
      }
    },
    "f7f21698-652b-4ff2-96de-9917ab786b5a": {
      "type": "home-featured-products",
      "settings": {
        "title": "Mira nuestros productos destacados",
        "coll": "carrusel"
      }
    },
    "46b57673-ac3d-42a2-b9b3-a344ff270a39": {
      "type": "home-categorias",
      "blocks": {
        "ba010b25-44dd-4715-8b7c-9904ee8e62fc": {
          "type": "category",
          "settings": {
            "image": "shopify:\/\/shop_images\/mantas_4ef46d6b-f0e2-4ad4-b992-6cad8cf1b3be.jpg",
            "coll": "mantas-electricas"
          }
        },
        "9cbfa717-f33a-4bf5-85f2-2de5eb24ef02": {
          "type": "category",
          "settings": {
            "image": "shopify:\/\/shop_images\/calientacamas1.jpg",
            "coll": "calientacamas"
          }
        },
        "69d1963f-d9d7-4db4-a88e-8f3514fbf24e": {
          "type": "category",
          "settings": {
            "image": "shopify:\/\/shop_images\/almohadillas_6c07a361-6d47-4578-ad55-714662db9e50.jpg",
            "coll": "almohadillas"
          }
        }
      },
      "block_order": [
        "ba010b25-44dd-4715-8b7c-9904ee8e62fc",
        "9cbfa717-f33a-4bf5-85f2-2de5eb24ef02",
        "69d1963f-d9d7-4db4-a88e-8f3514fbf24e"
      ],
      "settings": {}
    },
    "9f59a0f5-bef0-461f-b495-bb7df5637ff9": {
      "type": "home-full-width-image",
      "disabled": true,
      "settings": {
        "image_desktop": "shopify:\/\/shop_images\/JULIO_SCALDASONNO-37.jpg",
        "image_mobile": "shopify:\/\/shop_images\/JULIO_SCALDASONNO-38.jpg",
        "link": "shopify:\/\/collections\/calor-que-conecta",
        "alt_text": ""
      }
    },
    "26118325-e776-4745-970d-3d17469317ee": {
      "type": "home-beneficios",
      "blocks": {
        "b28f7bed-ad9f-4daf-b085-41578d3ac867": {
          "type": "beneficio",
          "settings": {
            "image": "shopify:\/\/shop_images\/Sin_titulo-2_2.png",
            "title": "Regenerador",
            "content": "<p>La manta eléctrica ha valorizado el relax con el confort del calor que nos acaricia.<\/p>"
          }
        },
        "3dcee0c6-7cd9-42ed-894f-05f45c9d6d96": {
          "type": "beneficio",
          "settings": {
            "image": "shopify:\/\/shop_images\/55555-03_1.png",
            "title": "Relajante",
            "content": "<p>El calientacamas de Imetec ha cambiado el modo de dormir, favoreciendo un sueño de calidad gracias al calor personalizado.<\/p>"
          }
        },
        "3eeaf776-8bc2-4478-9634-e0e1c07c1cf4": {
          "type": "beneficio",
          "settings": {
            "image": "shopify:\/\/shop_images\/55555-02_1.png",
            "title": "Bienestar",
            "content": "<p>La nueva generación de almohadillas eléctricas ha evolucionado para mejorar la calidad de vida y el bienestar gracias al calor inteligente<\/p>"
          }
        }
      },
      "block_order": [
        "b28f7bed-ad9f-4daf-b085-41578d3ac867",
        "3dcee0c6-7cd9-42ed-894f-05f45c9d6d96",
        "3eeaf776-8bc2-4478-9634-e0e1c07c1cf4"
      ],
      "settings": {
        "title": "Experimenta los Beneficios del calor",
        "content": "<p>El calor es una fuente de bienestar que brinda muchos beneficios al cuerpo. El calor liberado por los productos Scaldasonno facilita la circulación sanguínea, favorece la relajación y la reducción de las tensiones musculares entregando seguridad a través de las innovaciones tecnológicas, diseño y calidad.<\/p>"
      }
    },
    "ced39aef-4ee6-41f4-b01d-7347f25e682a": {
      "type": "featured-articles",
      "blocks": {
        "8b9f2151-8a72-4ff4-8d6b-85d2377feab0": {
          "type": "featured",
          "settings": {
            "article": "noticias\/lorem-ipsum-dolor-sit-amet-1"
          }
        },
        "32133191-4a21-4d17-a3c2-9f9f683cd998": {
          "type": "featured",
          "settings": {
            "article": "noticias\/lorem-ipsum-dolor"
          }
        },
        "ba7c538b-cfbd-4c55-b774-70dbe53a93c0": {
          "type": "featured",
          "settings": {
            "article": "noticias\/lorem-ipsum-dolor-sit-amet"
          }
        }
      },
      "block_order": [
        "8b9f2151-8a72-4ff4-8d6b-85d2377feab0",
        "32133191-4a21-4d17-a3c2-9f9f683cd998",
        "ba7c538b-cfbd-4c55-b774-70dbe53a93c0"
      ],
      "settings": {
        "title": "Mira Nuestro Blog",
        "link_blog": "shopify:\/\/blogs\/noticias"
      }
    },
    "e3d8d3d8-1d4b-4452-b6bd-ef718fa34de7": {
      "type": "home-sellos",
      "blocks": {
        "0acf1b3d-43f4-4643-afdf-d76295834596": {
          "type": "sello",
          "settings": {
            "image": "shopify:\/\/shop_images\/0220_1.png",
            "title": "Máxima seguridad",
            "content": "Todos los productos Imetec cumplen con las altas y estrictas normas internacionales de seguridad incluyendo el exclusivo dispositivo de seguridad total \"Electro Block\"®.",
            "link": ""
          }
        },
        "d1cbee44-9e53-4b80-8b6c-111a395aba99": {
          "type": "sello",
          "settings": {
            "image": "shopify:\/\/shop_images\/030_1.png",
            "title": "40 años de experiencia",
            "content": "Scaldasonno es una marca de Imetec, empresa italiana líder  con más de 40 años de experiencia en el mercado. El compromiso constante en investigación y desarrollo garantiza la innovación tecnológica de vanguardia que destaca la seguridad, prestaciones y calidad en sus textiles.",
            "link": ""
          }
        },
        "8b72e4fd-a39e-4af5-aa44-07150364c57f": {
          "type": "sello",
          "settings": {
            "image": "shopify:\/\/shop_images\/011_1.png",
            "title": "Máxima Comodidad",
            "content": "En Imetec nos preocupamos de entregarte la máxima protección y comodidad. Todos nuestros productos de Imetec cuentan con tecnología térmica desarrollada en Italia, textiles de alta calidad, prestaciones personalizadas y programables.",
            "link": ""
          }
        }
      },
      "block_order": [
        "0acf1b3d-43f4-4643-afdf-d76295834596",
        "d1cbee44-9e53-4b80-8b6c-111a395aba99",
        "8b72e4fd-a39e-4af5-aa44-07150364c57f"
      ],
      "settings": {}
    },
    "1674754739960fe6b0": {
      "type": "apps",
      "blocks": {
        "df0b75c3-2618-4233-aec4-28c44a1917d1": {
          "type": "shopify:\/\/apps\/instafeed\/blocks\/app-block\/c447db20-095d-4a10-9725-b5977662c9d5",
          "settings": {
            "title": "",
            "title_color": "",
            "alignment": "center",
            "background_color": "",
            "feed_id": "",
            "html_area": ""
          }
        }
      },
      "block_order": [
        "df0b75c3-2618-4233-aec4-28c44a1917d1"
      ],
      "settings": {
        "include_margins": false
      }
    },
    "bc75def8-a32d-46b8-96b4-3ae1d718503e": {
      "type": "home-newsletter",
      "settings": {
        "title": "Entérate de todas nuestras novedades, sé parte del mundo scaldasonno imetec bienestar",
        "content": "<p>Suscribete al boletín informativo para recibir adelantos sobre las novedades del mundo Scaldasonno y de las ofertas especiales<\/p>"
      }
    }
  },
  "order": [
    "15d9c212-6ce8-4fd0-9cf9-c773090bb162",
    "4e0fee28-e16c-4802-9402-cc8e410a5f50",
    "countdown_TiaGXg",
    "main",
    "6d039727-5eef-443e-a084-d2a448f903cb",
    "f7f21698-652b-4ff2-96de-9917ab786b5a",
    "46b57673-ac3d-42a2-b9b3-a344ff270a39",
    "9f59a0f5-bef0-461f-b495-bb7df5637ff9",
    "26118325-e776-4745-970d-3d17469317ee",
    "ced39aef-4ee6-41f4-b01d-7347f25e682a",
    "e3d8d3d8-1d4b-4452-b6bd-ef718fa34de7",
    "1674754739960fe6b0",
    "bc75def8-a32d-46b8-96b4-3ae1d718503e"
  ]
}
